zettel/__init__.py
zettel/cli.py
zettel/notebook.py
zettel/notes.py
zettel-0.0.0.post9000.dist-info/METADATA
zettel-0.0.0.post9000.dist-info/WHEEL
zettel-0.0.0.post9000.dist-info/RECORD
