Metadata-Version: 2.1
Name: zettel
Version: 0.0.0.post9000
Summary: A package for notetaking inspired by the zettelkasten method
